[
    {
        "id" :1,
        "idZona": 1,
        "nombreZona": "El Rincón",
        "slugZona": "el-rincon",
        "nombre" : "Nido de águila",
        "slug":"nido-de-aguila",
        "subtitulo" : "6 vías entre 5+ y 7b+",
        "imagen" : "bandurrias",
        "imagenSector": "rincon",
        "imagen3": "",
        "imagenLlegar": "el-rincon",
        "imagenMapa": "",
        "descripcion": "6 vías entre 5+ y 7b+ | xx a xxmts | x a x cintas",
        "llegar": "XXX",
        "vias": [
                {
                    "nombre": "Vachota",
                    "subtitulo": "",
                    "largo": "xxm",
                    "categoria1": "xx",
                    "categoria2": "4+",
                    "observaciones":"Multilargo"
                },
                {
                    "nombre": "Mano, Mano, Cabeza Afuera",
                    "subtitulo": "",
                    "largo": "XXm",
                    "categoria1": "xx",
                    "categoria2": "7b+",
                    "observaciones":"Multilargo"
                },
                {
                    "nombre": "Bachata",
                    "subtitulo": "",
                    "largo": "XXm",
                    "categoria1": "xx",
                    "categoria2": "5+",
                    "observaciones":""
                },
                {
                    "nombre": "Travesia Para llegar a Pie de Vía",
                    "subtitulo": "",
                    "largo": "XXm",
                    "categoria1": "5?",
                    "categoria2": "4-5?",
                    "observaciones":"Este se usa para llegar a un pie de via para hacer la Cascadisimo Forever y Gacela del hielo. En este pie de vía se debe estar asegurado todo el tiempo"
                },
                {
                    "nombre": "Cascadismo Forever",
                    "subtitulo": "",
                    "largo": "XXm",
                    "categoria1": "9?",
                    "categoria2": "6a",
                    "observaciones":"En el pie de vía se debe estar asegurado todo el tiempo"
                },
                {
                    "nombre": "La Gacela del Hielo",
                    "subtitulo": "",
                    "largo": "XXm",
                    "categoria1": "11?",
                    "categoria2": "6b+",
                    "observaciones":"En el pie de vía se debe estar asegurado todo el tiempo"
                }
        ]
    },
    {
        "id" : 1,
        "idZona": 1,
        "nombreZona": "Corrales Del infiernillo",
        "slugZona": "corrales-del-infiernillo",
        "nombre" : "Pasillo",
        "slug":"pasillo",
        "subtitulo" : "2 vías 6a",
        "imagen" : "corrales-del-infiernillo",
        "imagenSector": "pasillo",
        "imagen3": "",
        "imagenLlegar": "corrales-del-infiernillo",
        "imagenMapa": "",
        "descripcion": "4 vías entre 6a+ y 6c | xx a 25mts | x a x cintas",
        "llegar": "XXX",
        "vias": [
                {
                    "nombre": "Senpai",
                    "subtitulo": "Matías Rohmer - Luis González",
                    "largo": "25m",
                    "categoria1": "xx",
                    "categoria2": "6a+",
                    "observaciones":"Multilargo"
                },
                {
                    "nombre": "Mano, Mano, Cabeza Afuera",
                    "subtitulo": "",
                    "largo": "XXm",
                    "categoria1": "xx",
                    "categoria2": "7b+",
                    "observaciones":"Multilargo"
                },
                {
                    "nombre": "Bachata",
                    "subtitulo": "",
                    "largo": "XXm",
                    "categoria1": "xx",
                    "categoria2": "5+",
                    "observaciones":""
                },
                {
                    "nombre": "Travesia Para llegar a Pie de Vía",
                    "subtitulo": "",
                    "largo": "XXm",
                    "categoria1": "5?",
                    "categoria2": "4-5?",
                    "observaciones":"Este se usa para llegar a un pie de via para hacer la Cascadisimo Forever y Gacela del hielo. En este pie de vía se debe estar asegurado todo el tiempo"
                },
                {
                    "nombre": "Cascadismo Forever",
                    "subtitulo": "",
                    "largo": "XXm",
                    "categoria1": "9?",
                    "categoria2": "6a",
                    "observaciones":"En el pie de vía se debe estar asegurado todo el tiempo"
                },
                {
                    "nombre": "La Gacela del Hielo",
                    "subtitulo": "",
                    "largo": "XXm",
                    "categoria1": "11?",
                    "categoria2": "6b+",
                    "observaciones":"En el pie de vía se debe estar asegurado todo el tiempo"
                }
        ]
    }
]